cylc/uiserver/__init__.py
cylc/uiserver/app.py
cylc/uiserver/authorise.py
cylc/uiserver/config_util.py
cylc/uiserver/data_store_mgr.py
cylc/uiserver/handlers.py
cylc/uiserver/hubapp.py
cylc/uiserver/jupyter_config.py
cylc/uiserver/jupyterhub_config.py
cylc/uiserver/logging_util.py
cylc/uiserver/logo.svg
cylc/uiserver/py.typed
cylc/uiserver/resolvers.py
cylc/uiserver/schema.py
cylc/uiserver/utils.py
cylc/uiserver/workflows_mgr.py
cylc/uiserver/graphql/__init__.py
cylc/uiserver/graphql/tornado.py
cylc/uiserver/graphql/tornado_ws.py
cylc/uiserver/scripts/__init__.py
cylc/uiserver/scripts/gui.py
cylc/uiserver/scripts/hub.py
cylc/uiserver/scripts/hubapp.py
cylc/uiserver/tests/__init__.py
cylc/uiserver/tests/conftest.py
cylc/uiserver/tests/test_auth.py
cylc/uiserver/tests/test_authorise.py
cylc/uiserver/tests/test_config.py
cylc/uiserver/tests/test_data_store_mgr.py
cylc/uiserver/tests/test_graphql.py
cylc/uiserver/tests/test_gui.py
cylc/uiserver/tests/test_handlers.py
cylc/uiserver/tests/test_logging_util.py
cylc/uiserver/tests/test_resolvers.py
cylc/uiserver/tests/test_schema.py
cylc/uiserver/tests/test_uiserver.py
cylc/uiserver/tests/test_workflow_retrieval.py
cylc/uiserver/tests/test_workflows_mgr.py
cylc/uiserver/tests/test_workflows_mgr_data_store.py
cylc/uiserver/ui/2.10.0/favicon.png
cylc/uiserver/ui/2.10.0/fonts.css
cylc/uiserver/ui/2.10.0/index.html
cylc/uiserver/ui/2.10.0/assets/Analysis-BBHUYfhB.css
cylc/uiserver/ui/2.10.0/assets/Analysis-rqxW0vwZ.js
cylc/uiserver/ui/2.10.0/assets/Dashboard-DoexqeKQ.js
cylc/uiserver/ui/2.10.0/assets/Gantt-6P23AHY7.js
cylc/uiserver/ui/2.10.0/assets/Graph-BNXWiB3d.js
cylc/uiserver/ui/2.10.0/assets/Graph-BpCaD5tF.css
cylc/uiserver/ui/2.10.0/assets/GraphNode-CjrYIu24.js
cylc/uiserver/ui/2.10.0/assets/GraphiQL-BQoybdla.js
cylc/uiserver/ui/2.10.0/assets/GraphiQL-CySnTfGq.css
cylc/uiserver/ui/2.10.0/assets/Guide-CsdTh5zT.js
cylc/uiserver/ui/2.10.0/assets/Guide-FJEWHFTU.css
cylc/uiserver/ui/2.10.0/assets/Info-BNYm9LfD.css
cylc_uiserver-1.8.0.dist-info/licenses/COPYING
cylc_uiserver-1.8.0.dist-info/METADATA
cylc_uiserver-1.8.0.dist-info/WHEEL
cylc_uiserver-1.8.0.dist-info/entry_points.txt
cylc_uiserver-1.8.0.dist-info/top_level.txt
cylc_uiserver-1.8.0.dist-info/RECORD
