Metadata-Version: 2.4
Name: cylc-uiserver
Version: 1.8.0
Summary: Cylc UI Server
Home-page: https://github.com/cylc/cylc-uiserver/
License: GPL
Platform: any
Classifier: Environment :: Console
Classifier: Environment :: Web Environment
Classifier: Intended Audience :: Developers
Classifier: Intended Audience :: System Administrators
Classifier: Intended Audience :: Science/Research
Classifier: Topic :: Scientific/Engineering :: Atmospheric Science
Classifier: License :: OSI Approved :: GNU General Public License v3 (GPLv3)
Classifier: Operating System :: POSIX
Classifier: Programming Language :: Python
Classifier: Programming Language :: Python :: 3 :: Only
Classifier: Programming Language :: Python :: Implementation :: CPython
Requires-Python: >=3.12
License-File: COPYING
Requires-Dist: cylc-flow==8.6.*
Requires-Dist: ansimarkup>=1.0.0
Requires-Dist: jupyter_server>=2.13.0
Requires-Dist: requests
Requires-Dist: packaging
Requires-Dist: psutil
Requires-Dist: tornado>=6.5.0
Requires-Dist: traitlets>=5.2.1
Requires-Dist: pyzmq
Requires-Dist: graphene
Provides-Extra: hub
Requires-Dist: jupyterhub>=4; extra == "hub"
Provides-Extra: tests
Requires-Dist: coverage>=5.0.0; extra == "tests"
Requires-Dist: flake8-broken-line>=0.3.0; extra == "tests"
Requires-Dist: flake8-bugbear>=21.0.0; extra == "tests"
Requires-Dist: flake8-builtins>=1.5.0; extra == "tests"
Requires-Dist: flake8-comprehensions>=3.5.0; extra == "tests"
Requires-Dist: flake8-debugger>=4.0.0; extra == "tests"
Requires-Dist: flake8-mutable>=1.2.0; extra == "tests"
Requires-Dist: flake8-simplify>=0.14.0; extra == "tests"
Requires-Dist: flake8-type-checking; extra == "tests"
Requires-Dist: flake8>=3.0.0; extra == "tests"
Requires-Dist: jupyter_server[test]; extra == "tests"
Requires-Dist: mypy>=0.900; extra == "tests"
Requires-Dist: pytest-cov>=2.8.0; extra == "tests"
Requires-Dist: pytest-tornasync>=0.5.0; extra == "tests"
Requires-Dist: pytest<8.2,>=6; extra == "tests"
Requires-Dist: towncrier>=24.7.0; extra == "tests"
Requires-Dist: types-setuptools; extra == "tests"
Requires-Dist: types-requests>2; extra == "tests"
Provides-Extra: all
Requires-Dist: jupyterhub>=4; extra == "all"
Requires-Dist: coverage>=5.0.0; extra == "all"
Requires-Dist: flake8-broken-line>=0.3.0; extra == "all"
Requires-Dist: flake8-bugbear>=21.0.0; extra == "all"
Requires-Dist: flake8-builtins>=1.5.0; extra == "all"
Requires-Dist: flake8-comprehensions>=3.5.0; extra == "all"
Requires-Dist: flake8-debugger>=4.0.0; extra == "all"
Requires-Dist: flake8-mutable>=1.2.0; extra == "all"
Requires-Dist: flake8-simplify>=0.14.0; extra == "all"
Requires-Dist: flake8-type-checking; extra == "all"
Requires-Dist: flake8>=3.0.0; extra == "all"
Requires-Dist: jupyter_server[test]; extra == "all"
Requires-Dist: mypy>=0.900; extra == "all"
Requires-Dist: pytest-cov>=2.8.0; extra == "all"
Requires-Dist: pytest-tornasync>=0.5.0; extra == "all"
Requires-Dist: pytest<8.2,>=6; extra == "all"
Requires-Dist: towncrier>=24.7.0; extra == "all"
Requires-Dist: types-setuptools; extra == "all"
Requires-Dist: types-requests>2; extra == "all"
Dynamic: license-file
